understanding_imports/__init__.py
understanding_imports/directory_finder.py
understanding_imports/run.py
understanding_imports-0.3.0.dist-info/WHEEL
understanding_imports-0.3.0.dist-info/METADATA
understanding_imports-0.3.0.dist-info/RECORD
