Metadata-Version: 2.1
Name: understanding-imports
Version: 0.3.0
Summary: Fixing imports in Python
Author: Yashesh Dasari
Author-email: yasheshdasari@gmail.com
Requires-Python: >=3.6,<4.0
Classifier: Programming Language :: Python :: 3
Classifier: Programming Language :: Python :: 3.6
Classifier: Programming Language :: Python :: 3.7
Classifier: Programming Language :: Python :: 3.8
Classifier: Programming Language :: Python :: 3.9
Classifier: Programming Language :: Python :: 3.10
Classifier: Programming Language :: Python :: 3.11
Requires-Dist: pathsingleton (==0.1.0)
